{
    "examTime": 90,
    "examinationPaperTitle": "202403GESP 图形化三级试卷",
    "paperQuestionsVOS": [
        {
            "id": "1881967924403150849",
            "examinationPaperTitle": "202403GESP 图形化三级试卷",
            "type": 1,
            "title": "<p><span style=\"color: rgb(0, 0, 0);\">小杨的父母最近刚刚给他买了一块华为手表，他说手表上跑的是鸿蒙，这个鸿蒙是？（ ）</span></p>",
            "referenceAnswer": "C",
            "analyzeContent": "<p>分析设备运行的底层平台时，需识别其核心功能是否具备资源调度、硬件抽象、应用管理和用户交互能力。具备上述特征的软件层属于管理硬件与应用程序之间交互的系统级程序。此类程序为设备提供基础运行环境，支持应用开发与执行，并协调硬件资源分配。</p>",
            "analyzeVideo": null,
            "examinationPaperId": "1881967623252123650",
            "markStatus": 1,
            "stemId": null,
            "stemContent": null,
            "score": 2.0,
            "topSubjectDetailId": "1972940117698342914",
            "topSubjectDetailName": "图形化编程",
            "scoreCriteria": null,
            "createTime": "2025-01-22 15:31:33",
            "questionsOptionList": [
                {
                    "questionId": "1881967924403150849",
                    "questionOption": "A",
                    "questionOptionContent": "<p><span style=\"color: rgb(0, 0, 0);\">小程序</span></p>",
                    "questionOptionContentType": 1,
                    "sortNum": 1
                },
                {
                    "questionId": "1881967924403150849",
                    "questionOption": "B",
                    "questionOptionContent": "<p><span style=\"color: rgb(0, 0, 0);\">计时器</span></p>",
                    "questionOptionContentType": 1,
                    "sortNum": 2
                },
                {
                    "questionId": "1881967924403150849",
                    "questionOption": "C",
                    "questionOptionContent": "<p><span style=\"color: rgb(0, 0, 0);\">操作系统</span></p>",
                    "questionOptionContentType": 1,
                    "sortNum": 3
                },
                {
                    "questionId": "1881967924403150849",
                    "questionOption": "D",
                    "questionOptionContent": "<p><span style=\"color: rgb(0, 0, 0);\">神话人物</span></p>",
                    "questionOptionContentType": 1,
                    "sortNum": 4
                }
            ],
            "questionsKnowledgePointList": [
                {
                    "questionId": "1881967924403150849",
                    "knowledgePointId": "430",
                    "knowledgePoint": "计算机的输入、输出功能"
                }
            ],
            "questionsDetailDTO": null
        },
        {
            "id": "1881968083975065602",
            "examinationPaperTitle": "202403GESP 图形化三级试卷",
            "type": 1,
            "title": "<p><span style=\"color: rgb(0, 0, 0);\">下列流程图的输出结果是？( )</span></p><p><img src=\"https://minio.liankexue.cn/npsc-common-bucket/default/2025-01-22-15-31-55/8570309032806694912.png\" alt=\"\" data-href=\"\" style=\"\"/></p>",
            "referenceAnswer": "B",
            "analyzeContent": "<p><br></p>",
            "analyzeVideo": null,
            "examinationPaperId": "1881967623252123650",
            "markStatus": 1,
            "stemId": null,
            "stemContent": null,
            "score": 2.0,
            "topSubjectDetailId": "1972940117698342914",
            "topSubjectDetailName": "图形化编程",
            "scoreCriteria": null,
            "createTime": "2025-01-22 15:32:11",
            "questionsOptionList": [
                {
                    "questionId": "1881968083975065602",
                    "questionOption": "A",
                    "questionOptionContent": "<p>25</p>",
                    "questionOptionContentType": 1,
                    "sortNum": 1
                },
                {
                    "questionId": "1881968083975065602",
                    "questionOption": "B",
                    "questionOptionContent": "<p>30</p>",
                    "questionOptionContentType": 1,
                    "sortNum": 2
                },
                {
                    "questionId": "1881968083975065602",
                    "questionOption": "C",
                    "questionOptionContent": "<p>35</p>",
                    "questionOptionContentType": 1,
                    "sortNum": 3
                },
                {
                    "questionId": "1881968083975065602",
                    "questionOption": "D",
                    "questionOptionContent": "<p>55</p>",
                    "questionOptionContentType": 1,
                    "sortNum": 4
                }
            ],
            "questionsKnowledgePointList": [
                {
                    "questionId": "1881968083975065602",
                    "knowledgePointId": "439",
                    "knowledgePoint": "嵌套结构的流程图画法"
                },
                {
                    "questionId": "1881968083975065602",
                    "knowledgePointId": "440",
                    "knowledgePoint": "图形化编程中的逻辑推理能力"
                }
            ],
            "questionsDetailDTO": null
        },
        {
            "id": "1881968223572643842",
            "examinationPaperTitle": "202403GESP 图形化三级试卷",
            "type": 1,
            "title": "<p><span style=\"color: rgb(0, 0, 0);\">默认小猫角色，执行下列程序，绘制出如下图形，红框处填写的数值是？( )</span></p><p><img src=\"https://minio.liankexue.cn/npsc-common-bucket/default/2025-01-22-15-32-23/8570309152692486144.png\" alt=\"3-1.png\" data-href=\"https://minio.liankexue.cn/npsc-common-bucket/default/2025-01-22-15-32-23/8570309152692486144.png\" style=\"\"/><img src=\"https://minio.liankexue.cn/npsc-common-bucket/default/2025-01-22-15-32-28/8570309170560221184.png\" alt=\"3-2.png\" data-href=\"https://minio.liankexue.cn/npsc-common-bucket/default/2025-01-22-15-32-28/8570309170560221184.png\" style=\"\"/></p>",
            "referenceAnswer": "A",
            "analyzeContent": "<p><br></p>",
            "analyzeVideo": null,
            "examinationPaperId": "1881967623252123650",
            "markStatus": 1,
            "stemId": null,
            "stemContent": null,
            "score": 2.0,
            "topSubjectDetailId": "1972940117698342914",
            "topSubjectDetailName": "图形化编程",
            "scoreCriteria": null,
            "createTime": "2025-01-22 15:32:44",
            "questionsOptionList": [
                {
                    "questionId": "1881968223572643842",
                    "questionOption": "A",
                    "questionOptionContent": "<p>9</p>",
                    "questionOptionContentType": 1,
                    "sortNum": 1
                },
                {
                    "questionId": "1881968223572643842",
                    "questionOption": "B",
                    "questionOptionContent": "<p>8</p>",
                    "questionOptionContentType": 1,
                    "sortNum": 2
                },
                {
                    "questionId": "1881968223572643842",
                    "questionOption": "C",
                    "questionOptionContent": "<p>7</p>",
                    "questionOptionContentType": 1,
                    "sortNum": 3
                },
                {
                    "questionId": "1881968223572643842",
                    "questionOption": "D",
                    "questionOptionContent": "<p>5</p>",
                    "questionOptionContentType": 1,
                    "sortNum": 4
                }
            ],
            "questionsKnowledgePointList": [
                {
                    "questionId": "1881968223572643842",
                    "knowledgePointId": "440",
                    "knowledgePoint": "图形化编程中的逻辑推理能力"
                },
                {
                    "questionId": "1881968223572643842",
                    "knowledgePointId": "438",
                    "knowledgePoint": "嵌套的概念、特征与意义"
                },
                {
                    "questionId": "1881968223572643842",
                    "knowledgePointId": "439",
                    "knowledgePoint": "嵌套结构的流程图画法"
                }
            ],
            "questionsDetailDTO": null
        },
        {
            "id": "1881968351540858882",
            "examinationPaperTitle": "202403GESP 图形化三级试卷",
            "type": 1,
            "title": "<p><span style=\"color: rgb(0, 0, 0);\">默认小猫角色，执行下列程序，绘制出来的图形是？( )</span></p><p><img src=\"https://minio.liankexue.cn/npsc-common-bucket/default/2025-01-22-15-32-56/8570309287367393280.png\" alt=\"4.png\" data-href=\"https://minio.liankexue.cn/npsc-common-bucket/default/2025-01-22-15-32-56/8570309287367393280.png\" style=\"\"/></p>",
            "referenceAnswer": "C",
            "analyzeContent": "<p><br></p>",
            "analyzeVideo": null,
            "examinationPaperId": "1881967623252123650",
            "markStatus": 1,
            "stemId": null,
            "stemContent": null,
            "score": 2.0,
            "topSubjectDetailId": "1972940117698342914",
            "topSubjectDetailName": "图形化编程",
            "scoreCriteria": null,
            "createTime": "2025-01-22 15:33:15",
            "questionsOptionList": [
                {
                    "questionId": "1881968351540858882",
                    "questionOption": "A",
                    "questionOptionContent": "<p><img src=\"https://minio.liankexue.cn/npsc-common-bucket/default/2025-01-22-15-32-59/8570309301527363584.png\" alt=\"4A.png\" data-href=\"https://minio.liankexue.cn/npsc-common-bucket/default/2025-01-22-15-32-59/8570309301527363584.png\" style=\"\"/></p>",
                    "questionOptionContentType": 2,
                    "sortNum": 1
                },
                {
                    "questionId": "1881968351540858882",
                    "questionOption": "B",
                    "questionOptionContent": "<p><img src=\"https://minio.liankexue.cn/npsc-common-bucket/default/2025-01-22-15-33-03/8570309319508320256.png\" alt=\"4B.png\" data-href=\"https://minio.liankexue.cn/npsc-common-bucket/default/2025-01-22-15-33-03/8570309319508320256.png\" style=\"\"/></p>",
                    "questionOptionContentType": 2,
                    "sortNum": 2
                },
                {
                    "questionId": "1881968351540858882",
                    "questionOption": "C",
                    "questionOptionContent": "<p><img src=\"https://minio.liankexue.cn/npsc-common-bucket/default/2025-01-22-15-33-07/8570309333462794240.png\" alt=\"4C.png\" data-href=\"https://minio.liankexue.cn/npsc-common-bucket/default/2025-01-22-15-33-07/8570309333462794240.png\" style=\"\"/></p>",
                    "questionOptionContentType": 2,
                    "sortNum": 3
                },
                {
                    "questionId": "1881968351540858882",
                    "questionOption": "D",
                    "questionOptionContent": "<p><img src=\"https://minio.liankexue.cn/npsc-common-bucket/default/2025-01-22-15-33-11/8570309351775125504.png\" alt=\"4D.png\" data-href=\"https://minio.liankexue.cn/npsc-common-bucket/default/2025-01-22-15-33-11/8570309351775125504.png\" style=\"\"/></p>",
                    "questionOptionContentType": 2,
                    "sortNum": 4
                }
            ],
            "questionsKnowledgePointList": [
                {
                    "questionId": "1881968351540858882",
                    "knowledgePointId": "440",
                    "knowledgePoint": "图形化编程中的逻辑推理能力"
                },
                {
                    "questionId": "1881968351540858882",
                    "knowledgePointId": "438",
                    "knowledgePoint": "嵌套的概念、特征与意义"
                },
                {
                    "questionId": "1881968351540858882",
                    "knowledgePointId": "439",
                    "knowledgePoint": "嵌套结构的流程图画法"
                }
            ],
            "questionsDetailDTO": null
        },
        {
            "id": "1881968463090196481",
            "examinationPaperTitle": "202403GESP 图形化三级试卷",
            "type": 1,
            "title": "<p><span style=\"color: rgb(0, 0, 0);\">默认小猫角色，执行下列程序，输入数字 5，小猫说出的内容是？（ ）</span></p><p><img src=\"https://minio.liankexue.cn/npsc-common-bucket/default/2025-01-22-15-33-26/8570309416409350144.png\" alt=\"5.png\" data-href=\"https://minio.liankexue.cn/npsc-common-bucket/default/2025-01-22-15-33-26/8570309416409350144.png\" style=\"\"/></p>",
            "referenceAnswer": "A",
            "analyzeContent": "<p><br></p>",
            "analyzeVideo": null,
            "examinationPaperId": "1881967623252123650",
            "markStatus": 1,
            "stemId": null,
            "stemContent": null,
            "score": 2.0,
            "topSubjectDetailId": "1972940117698342914",
            "topSubjectDetailName": "图形化编程",
            "scoreCriteria": null,
            "createTime": "2025-01-22 15:33:42",
            "questionsOptionList": [
                {
                    "questionId": "1881968463090196481",
                    "questionOption": "A",
                    "questionOptionContent": "<p>12</p>",
                    "questionOptionContentType": 1,
                    "sortNum": 1
                },
                {
                    "questionId": "1881968463090196481",
                    "questionOption": "B",
                    "questionOptionContent": "<p>10</p>",
                    "questionOptionContentType": 1,
                    "sortNum": 2
                },
                {
                    "questionId": "1881968463090196481",
                    "questionOption": "C",
                    "questionOptionContent": "<p>8</p>",
                    "questionOptionContentType": 1,
                    "sortNum": 3
                },
                {
                    "questionId": "1881968463090196481",
                    "questionOption": "D",
                    "questionOptionContent": "<p>14</p>",
                    "questionOptionContentType": 1,
                    "sortNum": 4
                }
            ],
            "questionsKnowledgePointList": [
                {
                    "questionId": "1881968463090196481",
                    "knowledgePointId": "430",
                    "knowledgePoint": "计算机的输入、输出功能"
                },
                {
                    "questionId": "1881968463090196481",
                    "knowledgePointId": "431",
                    "knowledgePoint": "程序交互设计技巧"
                },
                {
                    "questionId": "1881968463090196481",
                    "knowledgePointId": "432",
                    "knowledgePoint": "字符串的概念"
                },
                {
                    "questionId": "1881968463090196481",
                    "knowledgePointId": "433",
                    "knowledgePoint": "字符串的常用操作"
                },
                {
                    "questionId": "1881968463090196481",
                    "knowledgePointId": "434",
                    "knowledgePoint": "列表的概念"
                },
                {
                    "questionId": "1881968463090196481",
                    "knowledgePointId": "435",
                    "knowledgePoint": "列表的定义、存储、插入、删除"
                },
                {
                    "questionId": "1881968463090196481",
                    "knowledgePointId": "438",
                    "knowledgePoint": "嵌套的概念、特征与意义"
                },
                {
                    "questionId": "1881968463090196481",
                    "knowledgePointId": "439",
                    "knowledgePoint": "嵌套结构的流程图画法"
                },
                {
                    "questionId": "1881968463090196481",
                    "knowledgePointId": "440",
                    "knowledgePoint": "图形化编程中的逻辑推理能力"
                }
            ],
            "questionsDetailDTO": null
        },
        {
            "id": "1881968561739845633",
            "examinationPaperTitle": "202403GESP 图形化三级试卷",
            "type": 1,
            "title": "<p><span style=\"color: rgb(0, 0, 0);\">默认小猫角色，执行下列程序，小猫说出的内容是？（ ）</span></p><p><img src=\"https://minio.liankexue.cn/npsc-common-bucket/default/2025-01-22-15-33-52/8570309525897437184.png\" alt=\"6.png\" data-href=\"https://minio.liankexue.cn/npsc-common-bucket/default/2025-01-22-15-33-52/8570309525897437184.png\" style=\"\"/></p>",
            "referenceAnswer": "D",
            "analyzeContent": "<p><br></p>",
            "analyzeVideo": null,
            "examinationPaperId": "1881967623252123650",
            "markStatus": 1,
            "stemId": null,
            "stemContent": null,
            "score": 2.0,
            "topSubjectDetailId": "1972940117698342914",
            "topSubjectDetailName": "图形化编程",
            "scoreCriteria": null,
            "createTime": "2025-01-22 15:34:05",
            "questionsOptionList": [
                {
                    "questionId": "1881968561739845633",
                    "questionOption": "A",
                    "questionOptionContent": "<p>2</p>",
                    "questionOptionContentType": 1,
                    "sortNum": 1
                },
                {
                    "questionId": "1881968561739845633",
                    "questionOption": "B",
                    "questionOptionContent": "<p>11</p>",
                    "questionOptionContentType": 1,
                    "sortNum": 2
                },
                {
                    "questionId": "1881968561739845633",
                    "questionOption": "C",
                    "questionOptionContent": "<p>34</p>",
                    "questionOptionContentType": 1,
                    "sortNum": 3
                },
                {
                    "questionId": "1881968561739845633",
                    "questionOption": "D",
                    "questionOptionContent": "<p>1111</p>",
                    "questionOptionContentType": 1,
                    "sortNum": 4
                }
            ],
            "questionsKnowledgePointList": [
                {
                    "questionId": "1881968561739845633",
                    "knowledgePointId": "433",
                    "knowledgePoint": "字符串的常用操作"
                },
                {
                    "questionId": "1881968561739845633",
                    "knowledgePointId": "431",
                    "knowledgePoint": "程序交互设计技巧"
                },
                {
                    "questionId": "1881968561739845633",
                    "knowledgePointId": "430",
                    "knowledgePoint": "计算机的输入、输出功能"
                }
            ],
            "questionsDetailDTO": null
        },
        {
            "id": "1881968672778407938",
            "examinationPaperTitle": "202403GESP 图形化三级试卷",
            "type": 1,
            "title": "<p><span style=\"color: rgb(0, 0, 0);\">默认小猫角色，执行下列程序，小猫说出的内容是？（ ）</span></p><p><img src=\"https://minio.liankexue.cn/npsc-common-bucket/default/2025-01-22-15-34-14/8570309616381157376.png\" alt=\"\" data-href=\"\" style=\"\"/></p>",
            "referenceAnswer": "D",
            "analyzeContent": "<p><br></p>",
            "analyzeVideo": null,
            "examinationPaperId": "1881967623252123650",
            "markStatus": 1,
            "stemId": null,
            "stemContent": null,
            "score": 2.0,
            "topSubjectDetailId": "1972940117698342914",
            "topSubjectDetailName": "图形化编程",
            "scoreCriteria": null,
            "createTime": "2025-01-22 15:34:32",
            "questionsOptionList": [
                {
                    "questionId": "1881968672778407938",
                    "questionOption": "A",
                    "questionOptionContent": "<p><span style=\"color: rgb(0, 0, 0);\">bananas</span></p>",
                    "questionOptionContentType": 1,
                    "sortNum": 1
                },
                {
                    "questionId": "1881968672778407938",
                    "questionOption": "B",
                    "questionOptionContent": "<p><span style=\"color: rgb(0, 0, 0);\">banana</span></p>",
                    "questionOptionContentType": 1,
                    "sortNum": 2
                },
                {
                    "questionId": "1881968672778407938",
                    "questionOption": "C",
                    "questionOptionContent": "<p><span style=\"color: rgb(0, 0, 0);\">sananab</span></p>",
                    "questionOptionContentType": 1,
                    "sortNum": 3
                },
                {
                    "questionId": "1881968672778407938",
                    "questionOption": "D",
                    "questionOptionContent": "<p><span style=\"color: rgb(0, 0, 0);\">ananab</span></p>",
                    "questionOptionContentType": 1,
                    "sortNum": 4
                }
            ],
            "questionsKnowledgePointList": [
                {
                    "questionId": "1881968672778407938",
                    "knowledgePointId": "432",
                    "knowledgePoint": "字符串的概念"
                },
                {
                    "questionId": "1881968672778407938",
                    "knowledgePointId": "433",
                    "knowledgePoint": "字符串的常用操作"
                },
                {
                    "questionId": "1881968672778407938",
                    "knowledgePointId": "431",
                    "knowledgePoint": "程序交互设计技巧"
                }
            ],
            "questionsDetailDTO": null
        },
        {
            "id": "1881968806238408705",
            "examinationPaperTitle": "202403GESP 图形化三级试卷",
            "type": 1,
            "title": "<p><span style=\"color: rgb(0, 0, 0);\">默认小猫角色，执行下列程序，列表 list 的第一项和第二项的值分别是？（ ）</span></p><p><img src=\"https://minio.liankexue.cn/npsc-common-bucket/default/2025-01-22-15-34-42/8570309733284823040.png\" alt=\"8.png\" data-href=\"https://minio.liankexue.cn/npsc-common-bucket/default/2025-01-22-15-34-42/8570309733284823040.png\" style=\"\"/></p>",
            "referenceAnswer": "A",
            "analyzeContent": "<p><br></p>",
            "analyzeVideo": null,
            "examinationPaperId": "1881967623252123650",
            "markStatus": 1,
            "stemId": null,
            "stemContent": null,
            "score": 2.0,
            "topSubjectDetailId": "1972940117698342914",
            "topSubjectDetailName": "图形化编程",
            "scoreCriteria": null,
            "createTime": "2025-01-22 15:35:03",
            "questionsOptionList": [
                {
                    "questionId": "1881968806238408705",
                    "questionOption": "A",
                    "questionOptionContent": "<p><span style=\"color: rgb(0, 0, 0);\">30 20</span></p>",
                    "questionOptionContentType": 1,
                    "sortNum": 1
                },
                {
                    "questionId": "1881968806238408705",
                    "questionOption": "B",
                    "questionOptionContent": "<p><span style=\"color: rgb(0, 0, 0);\">10 20</span></p>",
                    "questionOptionContentType": 1,
                    "sortNum": 2
                },
                {
                    "questionId": "1881968806238408705",
                    "questionOption": "C",
                    "questionOptionContent": "<p><span style=\"color: rgb(0, 0, 0);\">20 10</span></p>",
                    "questionOptionContentType": 1,
                    "sortNum": 3
                },
                {
                    "questionId": "1881968806238408705",
                    "questionOption": "D",
                    "questionOptionContent": "<p><span style=\"color: rgb(0, 0, 0);\">30 10</span></p>",
                    "questionOptionContentType": 1,
                    "sortNum": 4
                }
            ],
            "questionsKnowledgePointList": [
                {
                    "questionId": "1881968806238408705",
                    "knowledgePointId": "434",
                    "knowledgePoint": "列表的概念"
                },
                {
                    "questionId": "1881968806238408705",
                    "knowledgePointId": "435",
                    "knowledgePoint": "列表的定义、存储、插入、删除"
                },
                {
                    "questionId": "1881968806238408705",
                    "knowledgePointId": "440",
                    "knowledgePoint": "图形化编程中的逻辑推理能力"
                }
            ],
            "questionsDetailDTO": null
        },
        {
            "id": "1881968911086178306",
            "examinationPaperTitle": "202403GESP 图形化三级试卷",
            "type": 1,
            "title": "<p><span style=\"color: rgb(0, 0, 0);\">默认小猫角色，执行下列程序，变量“temp”的值为？（ ）</span></p><p><img src=\"https://minio.liankexue.cn/npsc-common-bucket/default/2025-01-22-15-35-14/8570309866311344128.png\" alt=\"9-1.png\" data-href=\"https://minio.liankexue.cn/npsc-common-bucket/default/2025-01-22-15-35-14/8570309866311344128.png\" style=\"\"/><img src=\"https://minio.liankexue.cn/npsc-common-bucket/default/2025-01-22-15-35-17/8570309879330463744.png\" alt=\"9-2.png\" data-href=\"https://minio.liankexue.cn/npsc-common-bucket/default/2025-01-22-15-35-17/8570309879330463744.png\" style=\"\"/></p>",
            "referenceAnswer": "D",
            "analyzeContent": "<p><br></p>",
            "analyzeVideo": null,
            "examinationPaperId": "1881967623252123650",
            "markStatus": 1,
            "stemId": null,
            "stemContent": null,
            "score": 2.0,
            "topSubjectDetailId": "1972940117698342914",
            "topSubjectDetailName": "图形化编程",
            "scoreCriteria": null,
            "createTime": "2025-01-22 15:35:28",
            "questionsOptionList": [
                {
                    "questionId": "1881968911086178306",
                    "questionOption": "A",
                    "questionOptionContent": "<p>9</p>",
                    "questionOptionContentType": 1,
                    "sortNum": 1
                },
                {
                    "questionId": "1881968911086178306",
                    "questionOption": "B",
                    "questionOptionContent": "<p>10</p>",
                    "questionOptionContentType": 1,
                    "sortNum": 2
                },
                {
                    "questionId": "1881968911086178306",
                    "questionOption": "C",
                    "questionOptionContent": "<p>11</p>",
                    "questionOptionContentType": 1,
                    "sortNum": 3
                },
                {
                    "questionId": "1881968911086178306",
                    "questionOption": "D",
                    "questionOptionContent": "<p>12</p>",
                    "questionOptionContentType": 1,
                    "sortNum": 4
                }
            ],
            "questionsKnowledgePointList": [
                {
                    "questionId": "1881968911086178306",
                    "knowledgePointId": "435",
                    "knowledgePoint": "变量的概念与使用"
                },
                {
                    "questionId": "1881968911086178306",
                    "knowledgePointId": "431",
                    "knowledgePoint": "程序交互设计技巧"
                },
                {
                    "questionId": "1881968911086178306",
                    "knowledgePointId": "440",
                    "knowledgePoint": "图形化编程中的逻辑推理能力"
                }
            ],
            "questionsDetailDTO": null
        },
        {
            "id": "1881969285643542530",
            "examinationPaperTitle": "202403GESP 图形化三级试卷",
            "type": 1,
            "title": "<p><span style=\"color: rgb(0, 0, 0);\">舞台中有小猫和 Apple 两个角色，执行下列小猫程序，舞台上最多会看到多少个苹果？（ ）</span></p><p><img src=\"https://minio.liankexue.cn/npsc-common-bucket/default/2025-01-22-15-35-42/8570309986608201728.png\" alt=\"10.png\" data-href=\"https://minio.liankexue.cn/npsc-common-bucket/default/2025-01-22-15-35-42/8570309986608201728.png\" style=\"\"/></p>",
            "referenceAnswer": "C",
            "analyzeContent": "<p><br></p>",
            "analyzeVideo": null,
            "examinationPaperId": "1881967623252123650",
            "markStatus": 1,
            "stemId": null,
            "stemContent": null,
            "score": 2.0,
            "topSubjectDetailId": "1972940117698342914",
            "topSubjectDetailName": "图形化编程",
            "scoreCriteria": null,
            "createTime": "2025-01-22 15:36:58",
            "questionsOptionList": [
                {
                    "questionId": "1881969285643542530",
                    "questionOption": "A",
                    "questionOptionContent": "<p><span style=\"color: rgb(0, 0, 0);\">10 个</span></p>",
                    "questionOptionContentType": 1,
                    "sortNum": 1
                },
                {
                    "questionId": "1881969285643542530",
                    "questionOption": "B",
                    "questionOptionContent": "<p><span style=\"color: rgb(0, 0, 0);\">11 个</span></p>",
                    "questionOptionContentType": 1,
                    "sortNum": 2
                },
                {
                    "questionId": "1881969285643542530",
                    "questionOption": "C",
                    "questionOptionContent": "<p><span style=\"color: rgb(0, 0, 0);\">1 个</span></p>",
                    "questionOptionContentType": 1,
                    "sortNum": 3
                },
                {
                    "questionId": "1881969285643542530",
                    "questionOption": "D",
                    "questionOptionContent": "<p><span style=\"color: rgb(0, 0, 0);\">无法确定</span></p>",
                    "questionOptionContentType": 1,
                    "sortNum": 4
                }
            ],
            "questionsKnowledgePointList": [
                {
                    "questionId": "1881969285643542530",
                    "knowledgePointId": "436",
                    "knowledgePoint": "克隆的私有变量"
                },
                {
                    "questionId": "1881969285643542530",
                    "knowledgePointId": "437",
                    "knowledgePoint": "二阶克隆"
                },
                {
                    "questionId": "1881969285643542530",
                    "knowledgePointId": "440",
                    "knowledgePoint": "图形化编程中的逻辑推理能力"
                }
            ],
            "questionsDetailDTO": null
        },
        {
            "id": "1881969421528780802",
            "examinationPaperTitle": "202403GESP 图形化三级试卷",
            "type": 1,
            "title": "<p><span style=\"color: rgb(0, 0, 0);\">默认小猫角色，执行下列程序，小猫说出的内容是？（ ）</span></p><p><img src=\"https://minio.liankexue.cn/npsc-common-bucket/default/2025-01-22-15-37-15/8570310373650161664.png\" alt=\"\" data-href=\"\" style=\"\"/></p>",
            "referenceAnswer": "B",
            "analyzeContent": "<p><br></p>",
            "analyzeVideo": null,
            "examinationPaperId": "1881967623252123650",
            "markStatus": 1,
            "stemId": null,
            "stemContent": null,
            "score": 2.0,
            "topSubjectDetailId": "1972940117698342914",
            "topSubjectDetailName": "图形化编程",
            "scoreCriteria": null,
            "createTime": "2025-01-22 15:37:30",
            "questionsOptionList": [
                {
                    "questionId": "1881969421528780802",
                    "questionOption": "A",
                    "questionOptionContent": "<p>14</p>",
                    "questionOptionContentType": 1,
                    "sortNum": 1
                },
                {
                    "questionId": "1881969421528780802",
                    "questionOption": "B",
                    "questionOptionContent": "<p>15</p>",
                    "questionOptionContentType": 1,
                    "sortNum": 2
                },
                {
                    "questionId": "1881969421528780802",
                    "questionOption": "C",
                    "questionOptionContent": "<p>16</p>",
                    "questionOptionContentType": 1,
                    "sortNum": 3
                },
                {
                    "questionId": "1881969421528780802",
                    "questionOption": "D",
                    "questionOptionContent": "<p>17</p>",
                    "questionOptionContentType": 1,
                    "sortNum": 4
                }
            ],
            "questionsKnowledgePointList": [
                {
                    "questionId": "1881969421528780802",
                    "knowledgePointId": "431",
                    "knowledgePoint": "程序交互设计技巧"
                },
                {
                    "questionId": "1881969421528780802",
                    "knowledgePointId": "430",
                    "knowledgePoint": "计算机的输入、输出功能"
                },
                {
                    "questionId": "1881969421528780802",
                    "knowledgePointId": "440",
                    "knowledgePoint": "图形化编程中的逻辑推理能力"
                }
            ],
            "questionsDetailDTO": null
        },
        {
            "id": "1881969561012183041",
            "examinationPaperTitle": "202403GESP 图形化三级试卷",
            "type": 1,
            "title": "<p><span style=\"color: rgb(0, 0, 0);\">默认小猫角色，执行下列程序，小猫说出的内容是？（ ）</span></p><p><img src=\"https://minio.liankexue.cn/npsc-common-bucket/default/2025-01-22-15-37-41/8570310485277392896.png\" alt=\"12.png\" data-href=\"https://minio.liankexue.cn/npsc-common-bucket/default/2025-01-22-15-37-41/8570310485277392896.png\" style=\"\"/></p>",
            "referenceAnswer": "C",
            "analyzeContent": "<p><br></p>",
            "analyzeVideo": null,
            "examinationPaperId": "1881967623252123650",
            "markStatus": 1,
            "stemId": null,
            "stemContent": null,
            "score": 2.0,
            "topSubjectDetailId": "1972940117698342914",
            "topSubjectDetailName": "图形化编程",
            "scoreCriteria": null,
            "createTime": "2025-01-22 15:38:03",
            "questionsOptionList": [
                {
                    "questionId": "1881969561012183041",
                    "questionOption": "A",
                    "questionOptionContent": "<p><span style=\"color: rgb(0, 0, 0);\">100</span></p>",
                    "questionOptionContentType": 1,
                    "sortNum": 1
                },
                {
                    "questionId": "1881969561012183041",
                    "questionOption": "B",
                    "questionOptionContent": "<p><span style=\"color: rgb(0, 0, 0);\">95</span></p>",
                    "questionOptionContentType": 1,
                    "sortNum": 2
                },
                {
                    "questionId": "1881969561012183041",
                    "questionOption": "C",
                    "questionOptionContent": "<p><span style=\"color: rgb(0, 0, 0);\">55</span></p>",
                    "questionOptionContentType": 1,
                    "sortNum": 3
                },
                {
                    "questionId": "1881969561012183041",
                    "questionOption": "D",
                    "questionOptionContent": "<p><span style=\"color: rgb(0, 0, 0);\">0</span></p>",
                    "questionOptionContentType": 1,
                    "sortNum": 4
                }
            ],
            "questionsKnowledgePointList": [
                {
                    "questionId": "1881969561012183041",
                    "knowledgePointId": "440",
                    "knowledgePoint": "图形化编程中的逻辑推理能力"
                },
                {
                    "questionId": "1881969561012183041",
                    "knowledgePointId": "433",
                    "knowledgePoint": "字符串的常用操作"
                }
            ],
            "questionsDetailDTO": null
        },
        {
            "id": "1881969707703390210",
            "examinationPaperTitle": "202403GESP 图形化三级试卷",
            "type": 1,
            "title": "<p><span style=\"color: rgb(0, 0, 0);\">下列两个积木的值分别是？（ ）</span></p><p><img src=\"https://minio.liankexue.cn/npsc-common-bucket/default/2025-01-22-15-38-17/8570310635139874816.png\" alt=\"13.png\" data-href=\"https://minio.liankexue.cn/npsc-common-bucket/default/2025-01-22-15-38-17/8570310635139874816.png\" style=\"\"/></p>",
            "referenceAnswer": "B",
            "analyzeContent": "<p><br></p>",
            "analyzeVideo": null,
            "examinationPaperId": "1881967623252123650",
            "markStatus": 1,
            "stemId": null,
            "stemContent": null,
            "score": 2.0,
            "topSubjectDetailId": "1972940117698342914",
            "topSubjectDetailName": "图形化编程",
            "scoreCriteria": null,
            "createTime": "2025-01-22 15:38:38",
            "questionsOptionList": [
                {
                    "questionId": "1881969707703390210",
                    "questionOption": "A",
                    "questionOptionContent": "<p><span style=\"color: rgb(0, 0, 0);\">false false</span></p>",
                    "questionOptionContentType": 1,
                    "sortNum": 1
                },
                {
                    "questionId": "1881969707703390210",
                    "questionOption": "B",
                    "questionOptionContent": "<p><span style=\"color: rgb(0, 0, 0);\">false true</span></p>",
                    "questionOptionContentType": 1,
                    "sortNum": 2
                },
                {
                    "questionId": "1881969707703390210",
                    "questionOption": "C",
                    "questionOptionContent": "<p><span style=\"color: rgb(0, 0, 0);\">true false</span></p>",
                    "questionOptionContentType": 1,
                    "sortNum": 3
                },
                {
                    "questionId": "1881969707703390210",
                    "questionOption": "D",
                    "questionOptionContent": "<p><span style=\"color: rgb(0, 0, 0);\">true true</span></p>",
                    "questionOptionContentType": 1,
                    "sortNum": 4
                }
            ],
            "questionsKnowledgePointList": [
                {
                    "questionId": "1881969707703390210",
                    "knowledgePointId": "430",
                    "knowledgePoint": "计算机的输入、输出功能"
                },
                {
                    "questionId": "1881969707703390210",
                    "knowledgePointId": "431",
                    "knowledgePoint": "程序交互设计技巧"
                },
                {
                    "questionId": "1881969707703390210",
                    "knowledgePointId": "440",
                    "knowledgePoint": "图形化编程中的逻辑推理能力"
                }
            ],
            "questionsDetailDTO": null
        },
        {
            "id": "1881969897894105089",
            "examinationPaperTitle": "202403GESP 图形化三级试卷",
            "type": 1,
            "title": "<p><span style=\"color: rgb(0, 0, 0);\">默认小猫角色，下列哪个选项可以表达该分段函数？（）</span></p><p><img src=\"https://minio.liankexue.cn/npsc-common-bucket/default/2025-01-22-15-39-04/8570310833014530048.png\" alt=\"14-1.png\" data-href=\"https://minio.liankexue.cn/npsc-common-bucket/default/2025-01-22-15-39-04/8570310833014530048.png\" style=\"\"/></p>",
            "referenceAnswer": "A",
            "analyzeContent": "<p><br></p>",
            "analyzeVideo": null,
            "examinationPaperId": "1881967623252123650",
            "markStatus": 1,
            "stemId": null,
            "stemContent": null,
            "score": 2.0,
            "topSubjectDetailId": "1972940117698342914",
            "topSubjectDetailName": "图形化编程",
            "scoreCriteria": null,
            "createTime": "2025-01-22 15:39:24",
            "questionsOptionList": [
                {
                    "questionId": "1881969897894105089",
                    "questionOption": "A",
                    "questionOptionContent": "<p><img src=\"https://minio.liankexue.cn/npsc-common-bucket/default/2025-01-22-15-39-10/8570310859157626880.png\" alt=\"14A.png\" data-href=\"https://minio.liankexue.cn/npsc-common-bucket/default/2025-01-22-15-39-10/8570310859157626880.png\" style=\"\"/></p>",
                    "questionOptionContentType": 2,
                    "sortNum": 1
                },
                {
                    "questionId": "1881969897894105089",
                    "questionOption": "B",
                    "questionOptionContent": "<p><img src=\"https://minio.liankexue.cn/npsc-common-bucket/default/2025-01-22-15-39-14/8570310875897118720.png\" alt=\"\" data-href=\"\" style=\"\"/></p>",
                    "questionOptionContentType": 2,
                    "sortNum": 2
                },
                {
                    "questionId": "1881969897894105089",
                    "questionOption": "C",
                    "questionOptionContent": "<p><img src=\"https://minio.liankexue.cn/npsc-common-bucket/default/2025-01-22-15-39-18/8570310889612468224.png\" alt=\"\" data-href=\"\" style=\"\"/></p>",
                    "questionOptionContentType": 2,
                    "sortNum": 3
                },
                {
                    "questionId": "1881969897894105089",
                    "questionOption": "D",
                    "questionOptionContent": "<p><img src=\"https://minio.liankexue.cn/npsc-common-bucket/default/2025-01-22-15-39-21/8570310904636465152.png\" alt=\"\" data-href=\"\" style=\"\"/></p>",
                    "questionOptionContentType": 2,
                    "sortNum": 4
                }
            ],
            "questionsKnowledgePointList": [
                {
                    "questionId": "1881969897894105089",
                    "knowledgePointId": "431",
                    "knowledgePoint": "程序交互设计技巧"
                },
                {
                    "questionId": "1881969897894105089",
                    "knowledgePointId": "440",
                    "knowledgePoint": "图形化编程中的逻辑推理能力"
                }
            ],
            "questionsDetailDTO": null
        },
        {
            "id": "1881970281631358977",
            "examinationPaperTitle": "202403GESP 图形化三级试卷",
            "type": 1,
            "title": "<p><span style=\"color: rgb(0, 0, 0);\">有 94 颗糖果，两人轮流拿，谁拿到最后一颗糖果谁输。条件是：每次最多拿 5颗，最少拿 1 颗。问先拿的人拿几颗糖果才能保证获胜？（ ）</span></p>",
            "referenceAnswer": "B",
            "analyzeContent": "<p><br></p>",
            "analyzeVideo": null,
            "examinationPaperId": "1881967623252123650",
            "markStatus": 1,
            "stemId": null,
            "stemContent": null,
            "score": 2.0,
            "topSubjectDetailId": "1972940117698342914",
            "topSubjectDetailName": "图形化编程",
            "scoreCriteria": null,
            "createTime": "2025-01-22 15:40:55",
            "questionsOptionList": [
                {
                    "questionId": "1881970281631358977",
                    "questionOption": "A",
                    "questionOptionContent": "<p><img src=\"https://minio.liankexue.cn/npsc-common-bucket/default/2025-01-22-15-40-24/8570311167669657600.png\" alt=\"\" data-href=\"\" style=\"\"/></p>",
                    "questionOptionContentType": 2,
                    "sortNum": 1
                },
                {
                    "questionId": "1881970281631358977",
                    "questionOption": "B",
                    "questionOptionContent": "<p><img src=\"https://minio.liankexue.cn/npsc-common-bucket/default/2025-01-22-15-40-18/8570311143489519616.png\" alt=\"15B.png\" data-href=\"https://minio.liankexue.cn/npsc-common-bucket/default/2025-01-22-15-40-18/8570311143489519616.png\" style=\"\"/></p>",
                    "questionOptionContentType": 2,
                    "sortNum": 2
                },
                {
                    "questionId": "1881970281631358977",
                    "questionOption": "C",
                    "questionOptionContent": "<p><img src=\"https://minio.liankexue.cn/npsc-common-bucket/default/2025-01-22-15-40-35/8570311215010766848.png\" alt=\"15C.png\" data-href=\"https://minio.liankexue.cn/npsc-common-bucket/default/2025-01-22-15-40-35/8570311215010766848.png\" style=\"\"/></p>",
                    "questionOptionContentType": 2,
                    "sortNum": 3
                },
                {
                    "questionId": "1881970281631358977",
                    "questionOption": "D",
                    "questionOptionContent": "<p><img src=\"https://minio.liankexue.cn/npsc-common-bucket/default/2025-01-22-15-40-50/8570311277782745088.png\" alt=\"15D.png\" data-href=\"https://minio.liankexue.cn/npsc-common-bucket/default/2025-01-22-15-40-50/8570311277782745088.png\" style=\"\"/></p>",
                    "questionOptionContentType": 2,
                    "sortNum": 4
                }
            ],
            "questionsKnowledgePointList": [
                {
                    "questionId": "1881970281631358977",
                    "knowledgePointId": "442",
                    "knowledgePoint": "枚举法"
                },
                {
                    "questionId": "1881970281631358977",
                    "knowledgePointId": "443",
                    "knowledgePoint": "模拟法"
                },
                {
                    "questionId": "1881970281631358977",
                    "knowledgePointId": "440",
                    "knowledgePoint": "图形化编程中的逻辑推理能力"
                }
            ],
            "questionsDetailDTO": null
        },
        {
            "id": "1881970503283167234",
            "examinationPaperTitle": "202403GESP 图形化三级试卷",
            "type": 3,
            "title": "<p>小杨今年春节回奶奶家了，奶奶家的数字电视要设置 ip 地址并接入到 WIFI 盒子才能收看节目，那这个 WIFI 盒子具有路由器的功能。（ ）</p>",
            "referenceAnswer": "1",
            "analyzeContent": "<p><br></p>",
            "analyzeVideo": null,
            "examinationPaperId": "1881967623252123650",
            "markStatus": 1,
            "stemId": null,
            "stemContent": null,
            "score": 2.0,
            "topSubjectDetailId": "1972940117698342914",
            "topSubjectDetailName": "图形化编程",
            "scoreCriteria": null,
            "createTime": "2025-01-22 15:41:48",
            "questionsOptionList": null,
            "questionsKnowledgePointList": [
                {
                    "questionId": "1881970503283167234",
                    "knowledgePointId": "2016158620672581634",
                    "knowledgePoint": "计算机基础知识"
                },
                {
                    "questionId": "1881970503283167234",
                    "knowledgePointId": "382",
                    "knowledgePoint": "计算机操作系统的使用"
                },
                {
                    "questionId": "1881970503283167234",
                    "knowledgePointId": "407",
                    "knowledgePoint": "计算机网络定义及其功能"
                }
            ],
            "questionsDetailDTO": null
        },
        {
            "id": "1881970592544903169",
            "examinationPaperTitle": "202403GESP 图形化三级试卷",
            "type": 3,
            "title": "<p><span style=\"color: rgb(0, 0, 0);\">默认小猫角色，执行下列代码，舞台上会出现 4 个一样大小的小猫。（ ）</span></p><p><img src=\"https://minio.liankexue.cn/npsc-common-bucket/default/2025-01-22-15-42-04/8570311586819039232.png\" alt=\"P2.png\" data-href=\"https://minio.liankexue.cn/npsc-common-bucket/default/2025-01-22-15-42-04/8570311586819039232.png\" style=\"\"/></p>",
            "referenceAnswer": "0",
            "analyzeContent": "<p><br></p>",
            "analyzeVideo": null,
            "examinationPaperId": "1881967623252123650",
            "markStatus": 1,
            "stemId": null,
            "stemContent": null,
            "score": 2.0,
            "topSubjectDetailId": "1972940117698342914",
            "topSubjectDetailName": "图形化编程",
            "scoreCriteria": null,
            "createTime": "2025-01-22 15:42:09",
            "questionsOptionList": null,
            "questionsKnowledgePointList": [
                {
                    "questionId": "1881970592544903169",
                    "knowledgePointId": "436",
                    "knowledgePoint": "克隆的私有变量"
                },
                {
                    "questionId": "1881970592544903169",
                    "knowledgePointId": "437",
                    "knowledgePoint": "二阶克隆"
                },
                {
                    "questionId": "1881970592544903169",
                    "knowledgePointId": "440",
                    "knowledgePoint": "图形化编程中的逻辑推理能力"
                }
            ],
            "questionsDetailDTO": null
        },
        {
            "id": "1881970645801422849",
            "examinationPaperTitle": "202403GESP 图形化三级试卷",
            "type": 3,
            "title": "<p>默认小猫角色，执行下列程序后，角色的坐标仍为（0,0）。（ ）</p><p><img src=\"https://minio.liankexue.cn/npsc-common-bucket/default/2025-01-22-15-42-18/8570311648554999808.png\"></p>",
            "referenceAnswer": "0",
            "analyzeContent": "<p><br></p>",
            "analyzeVideo": null,
            "examinationPaperId": "1881967623252123650",
            "markStatus": 1,
            "stemId": null,
            "stemContent": null,
            "score": 2.0,
            "topSubjectDetailId": "1972940117698342914",
            "topSubjectDetailName": "图形化编程",
            "scoreCriteria": null,
            "createTime": "2025-01-22 15:42:22",
            "questionsOptionList": null,
            "questionsKnowledgePointList": [
                {
                    "questionId": "1881970645801422849",
                    "knowledgePointId": "2016149710909726722",
                    "knowledgePoint": "数学基础运算"
                },
                {
                    "questionId": "1881970645801422849",
                    "knowledgePointId": "428",
                    "knowledgePoint": "算术运算、逻辑运算、关系运算"
                },
                {
                    "questionId": "1881970645801422849",
                    "knowledgePointId": "423",
                    "knowledgePoint": "广播的基本概念"
                }
            ],
            "questionsDetailDTO": null
        },
        {
            "id": "1881970707839373314",
            "examinationPaperTitle": "202403GESP 图形化三级试卷",
            "type": 3,
            "title": "<p>默认小猫角色，执行下列程序，小猫说 false，2 秒。（ ）</p><p><img src=\"https://minio.liankexue.cn/npsc-common-bucket/default/2025-01-22-15-42-33/8570311708458049536.png\"></p>",
            "referenceAnswer": "1",
            "analyzeContent": "<p><br></p>",
            "analyzeVideo": null,
            "examinationPaperId": "1881967623252123650",
            "markStatus": 1,
            "stemId": null,
            "stemContent": null,
            "score": 2.0,
            "topSubjectDetailId": "1972940117698342914",
            "topSubjectDetailName": "图形化编程",
            "scoreCriteria": null,
            "createTime": "2025-01-22 15:42:37",
            "questionsOptionList": null,
            "questionsKnowledgePointList": [
                {
                    "questionId": "1881970707839373314",
                    "knowledgePointId": "432",
                    "knowledgePoint": "字符串的概念"
                },
                {
                    "questionId": "1881970707839373314",
                    "knowledgePointId": "433",
                    "knowledgePoint": "字符串的常用操作"
                }
            ],
            "questionsDetailDTO": null
        },
        {
            "id": "1881970762390491138",
            "examinationPaperTitle": "202403GESP 图形化三级试卷",
            "type": 3,
            "title": "<p><span style=\"color: rgb(0, 0, 0);\">默认小猫角色，执行下列程序，可以删除列表中的所有项目。( )</span></p><p><img src=\"https://minio.liankexue.cn/npsc-common-bucket/default/2025-01-22-15-42-47/8570311766523994112.png\" alt=\"P5.png\" data-href=\"https://minio.liankexue.cn/npsc-common-bucket/default/2025-01-22-15-42-47/8570311766523994112.png\" style=\"\"/></p>",
            "referenceAnswer": "1",
            "analyzeContent": "<p><br></p>",
            "analyzeVideo": null,
            "examinationPaperId": "1881967623252123650",
            "markStatus": 1,
            "stemId": null,
            "stemContent": null,
            "score": 2.0,
            "topSubjectDetailId": "1972940117698342914",
            "topSubjectDetailName": "图形化编程",
            "scoreCriteria": null,
            "createTime": "2025-01-22 15:42:50",
            "questionsOptionList": null,
            "questionsKnowledgePointList": [
                {
                    "questionId": "1881970762390491138",
                    "knowledgePointId": "435",
                    "knowledgePoint": "列表的定义、存储、插入、删除"
                }
            ],
            "questionsDetailDTO": null
        },
        {
            "id": "1881970857521500161",
            "examinationPaperTitle": "202403GESP 图形化三级试卷",
            "type": 3,
            "title": "<p><span style=\"color: rgb(0, 0, 0);\">默认小猫角色，列表“星期”如左图所示，执行右图程序后，可以将“星期六”插入到该列表中并使一星期七天按先后顺序排列。（ ）</span></p><p><img src=\"https://minio.liankexue.cn/npsc-common-bucket/default/2025-01-22-15-43-05/8570311843221037056.png\" alt=\"P6-1.png\" data-href=\"https://minio.liankexue.cn/npsc-common-bucket/default/2025-01-22-15-43-05/8570311843221037056.png\" style=\"\"/><img src=\"https://minio.liankexue.cn/npsc-common-bucket/default/2025-01-22-15-43-09/8570311860614815744.png\" alt=\"P6-2.png\" data-href=\"https://minio.liankexue.cn/npsc-common-bucket/default/2025-01-22-15-43-09/8570311860614815744.png\" style=\"\"/></p>",
            "referenceAnswer": "1",
            "analyzeContent": "<p><br></p>",
            "analyzeVideo": null,
            "examinationPaperId": "1881967623252123650",
            "markStatus": 1,
            "stemId": null,
            "stemContent": null,
            "score": 2.0,
            "topSubjectDetailId": "1972940117698342914",
            "topSubjectDetailName": "图形化编程",
            "scoreCriteria": null,
            "createTime": "2025-01-22 15:43:12",
            "questionsOptionList": null,
            "questionsKnowledgePointList": [
                {
                    "questionId": "1881970857521500161",
                    "knowledgePointId": "434",
                    "knowledgePoint": "列表的概念"
                },
                {
                    "questionId": "1881970857521500161",
                    "knowledgePointId": "435",
                    "knowledgePoint": "列表的定义、存储、插入、删除"
                }
            ],
            "questionsDetailDTO": null
        },
        {
            "id": "1881971100886159362",
            "examinationPaperTitle": "202403GESP 图形化三级试卷",
            "type": 3,
            "title": "<p><span style=\"color: rgb(0, 0, 0);\">默认小猫角色，执行下列程序，舞台上出现 5 只小猫，无论点击哪只小猫，所有小猫都消失。（）</span></p><p><img src=\"https://minio.liankexue.cn/npsc-common-bucket/default/2025-01-22-15-44-06/8570312100654833664.png\" alt=\"7.png\" data-href=\"https://minio.liankexue.cn/npsc-common-bucket/default/2025-01-22-15-44-06/8570312100654833664.png\" style=\"\"/></p>",
            "referenceAnswer": "0",
            "analyzeContent": "<p><br></p>",
            "analyzeVideo": null,
            "examinationPaperId": "1881967623252123650",
            "markStatus": 1,
            "stemId": null,
            "stemContent": null,
            "score": 2.0,
            "topSubjectDetailId": "1972940117698342914",
            "topSubjectDetailName": "图形化编程",
            "scoreCriteria": null,
            "createTime": "2025-01-22 15:44:10",
            "questionsOptionList": null,
            "questionsKnowledgePointList": [
                {
                    "questionId": "1881971100886159362",
                    "knowledgePointId": "436",
                    "knowledgePoint": "克隆的私有变量"
                },
                {
                    "questionId": "1881971100886159362",
                    "knowledgePointId": "437",
                    "knowledgePoint": "二阶克隆"
                },
                {
                    "questionId": "1881971100886159362",
                    "knowledgePointId": "440",
                    "knowledgePoint": "图形化编程中的逻辑推理能力"
                }
            ],
            "questionsDetailDTO": null
        },
        {
            "id": "1881971178470023169",
            "examinationPaperTitle": "202403GESP 图形化三级试卷",
            "type": 3,
            "title": "<p>默认小猫角色，分别执行下列程序，小猫的运动状态是相同的。（ ）</p><p><img src=\"https://minio.liankexue.cn/npsc-common-bucket/default/2025-01-22-15-44-21/8570312162688589824.png\"><img src=\"https://minio.liankexue.cn/npsc-common-bucket/default/2025-01-22-15-44-25/8570312181336489984.png\"></p>",
            "referenceAnswer": "0",
            "analyzeContent": "<p><br></p>",
            "analyzeVideo": null,
            "examinationPaperId": "1881967623252123650",
            "markStatus": 1,
            "stemId": null,
            "stemContent": null,
            "score": 2.0,
            "topSubjectDetailId": "1972940117698342914",
            "topSubjectDetailName": "图形化编程",
            "scoreCriteria": null,
            "createTime": "2025-01-22 15:44:29",
            "questionsOptionList": null,
            "questionsKnowledgePointList": [
                {
                    "questionId": "1881971178470023169",
                    "knowledgePointId": "428",
                    "knowledgePoint": "算术运算、逻辑运算、关系运算"
                },
                {
                    "questionId": "1881971178470023169",
                    "knowledgePointId": "431",
                    "knowledgePoint": "程序交互设计技巧"
                }
            ],
            "questionsDetailDTO": null
        },
        {
            "id": "1881971299085623297",
            "examinationPaperTitle": "202403GESP 图形化三级试卷",
            "type": 3,
            "title": "<p><span style=\"color: rgb(0, 0, 0);\">假设变量 x，y，z 的值互不相等，默认小猫角色，执行下列程序，可以让 x，y，z 的值由小到大排序。（ ）</span></p><p><img src=\"https://minio.liankexue.cn/npsc-common-bucket/default/2025-01-22-15-44-53/8570312297397051392.png\" alt=\"\" data-href=\"\" style=\"\"/></p>",
            "referenceAnswer": "1",
            "analyzeContent": "<p><br></p>",
            "analyzeVideo": null,
            "examinationPaperId": "1881967623252123650",
            "markStatus": 1,
            "stemId": null,
            "stemContent": null,
            "score": 2.0,
            "topSubjectDetailId": "1972940117698342914",
            "topSubjectDetailName": "图形化编程",
            "scoreCriteria": null,
            "createTime": "2025-01-22 15:44:58",
            "questionsOptionList": null,
            "questionsKnowledgePointList": [
                {
                    "questionId": "1881971299085623297",
                    "knowledgePointId": "436",
                    "knowledgePoint": "变量的使用与操作"
                },
                {
                    "questionId": "1881971299085623297",
                    "knowledgePointId": "440",
                    "knowledgePoint": "逻辑推理"
                },
                {
                    "questionId": "1881971299085623297",
                    "knowledgePointId": "441",
                    "knowledgePoint": "基本数据结构"
                }
            ],
            "questionsDetailDTO": null
        },
        {
            "id": "1881971375019302914",
            "examinationPaperTitle": "202403GESP 图形化三级试卷",
            "type": 3,
            "title": "<p><span style=\"color: rgb(0, 0, 0);\">默认小猫角色，执行下列程序可以判断输入的整数是否为对称数，如 1221 是对称数，234 不是对称数。（ ）</span></p><p><img src=\"https://minio.liankexue.cn/npsc-common-bucket/default/2025-01-22-15-45-11/8570312370939977728.png\" alt=\"P10.png\" data-href=\"https://minio.liankexue.cn/npsc-common-bucket/default/2025-01-22-15-45-11/8570312370939977728.png\" style=\"\"/></p>",
            "referenceAnswer": "0",
            "analyzeContent": "<p><br></p>",
            "analyzeVideo": null,
            "examinationPaperId": "1881967623252123650",
            "markStatus": 1,
            "stemId": null,
            "stemContent": null,
            "score": 2.0,
            "topSubjectDetailId": "1972940117698342914",
            "topSubjectDetailName": "图形化编程",
            "scoreCriteria": null,
            "createTime": "2025-01-22 15:45:16",
            "questionsOptionList": null,
            "questionsKnowledgePointList": [
                {
                    "questionId": "1881971375019302914",
                    "knowledgePointId": "432",
                    "knowledgePoint": "字符串的概念"
                },
                {
                    "questionId": "1881971375019302914",
                    "knowledgePointId": "433",
                    "knowledgePoint": "字符串的常用操作"
                },
                {
                    "questionId": "1881971375019302914",
                    "knowledgePointId": "431",
                    "knowledgePoint": "程序交互设计技巧"
                },
                {
                    "questionId": "1881971375019302914",
                    "knowledgePointId": "430",
                    "knowledgePoint": "计算机的输入、输出功能"
                }
            ],
            "questionsDetailDTO": null
        },
        {
            "id": "1881972252767866881",
            "examinationPaperTitle": "202403GESP 图形化三级试卷",
            "type": 4,
            "title": "<p><span style=\"color: rgb(0, 0, 0);\">乘法问题</span></p><p><img src=\"https://minio.liankexue.cn/npsc-common-bucket/default/2025-01-22-15-47-01/8570312835203317760.png\" alt=\"\" data-href=\"\" style=\"\"/><img src=\"https://minio.liankexue.cn/npsc-common-bucket/default/2025-01-22-15-47-08/8570312863183495168.png\" alt=\"\" data-href=\"\" style=\"\"/></p><p><span style=\"color: rgb(0, 0, 0);\">【题目描述】 </span></p><p><span style=\"color: rgb(0, 0, 0);\">小杨刚刚学习了乘法，我们把若干个正整数（大于 1）存放到列表“list”中， </span></p><p><span style=\"color: rgb(0, 0, 0);\">要求他将这些数乘起来。 </span></p><p><span style=\"color: rgb(0, 0, 0);\">对于大部分题目，小杨可以精准地算出答案放入变量“result”中，不过，如果这些数的乘积超过 10000，小杨就不会做了，这时在变量“result”中存入 &gt;10000。 </span></p><p><span style=\"color: rgb(0, 0, 0);\">默认小猫角色和白色背景，请你写一个程序，告诉我们小杨会如何作答。 </span></p><p><span style=\"color: rgb(0, 0, 0);\">例如：若列表 list 最初存放的数据为[3, 5]，小杨计算完乘法后将 15 存入变量“result”中。若列表 list 最初存放的数据为[100, 100, 100]，小杨不会做，将 &gt;10000 存入变量“result”中。</span></p><p><span style=\"color: rgb(0, 0, 0);\">【输入描述】 </span></p><p><span style=\"color: rgb(0, 0, 0);\">新建列表“list”，用于存放需要进行乘法的数据。 </span></p><p><span style=\"color: rgb(0, 0, 0);\">如下图所示：</span></p><p><img src=\"https://minio.liankexue.cn/npsc-common-bucket/default/2025-01-22-15-47-50/8570313039436537856.png\" alt=\"\" data-href=\"\" style=\"\"/></p><p><span style=\"color: rgb(0, 0, 0);\">【输出描述】 </span></p><p><span style=\"color: rgb(0, 0, 0);\">新建变量“result”用于存储计算的结果，如果大于 10000，那么存入 &gt;10000，否则存入乘积的结果。 </span></p><p><span style=\"color: rgb(0, 0, 0);\">如下图所示：</span></p><p><img src=\"https://minio.liankexue.cn/npsc-common-bucket/default/2025-01-22-15-48-07/8570313111733755904.png\" alt=\"\" data-href=\"\" style=\"\"/></p><p><span style=\"color: rgb(0, 0, 0);\">【输入样例】 </span></p><p><span style=\"color: rgb(0, 0, 0);\">list = [100, 100, 100] </span></p><p><span style=\"color: rgb(0, 0, 0);\">【输出样例】 </span></p><p><span style=\"color: rgb(0, 0, 0);\">result = &gt;10000 </span></p><p><span style=\"color: rgb(0, 0, 0);\">【输入样例】 </span></p><p><span style=\"color: rgb(0, 0, 0);\">year = [3, 5] </span></p><p><span style=\"color: rgb(0, 0, 0);\">【输出样例】 </span></p><p><span style=\"color: rgb(0, 0, 0);\">result = 15</span></p><p><span style=\"color: rgb(255, 0, 0);\">注意事项： </span></p><p><span style=\"color: rgb(255, 0, 0);\">1、列表名、变量名的拼写（包括大小写）要和题目完全一致。 </span></p><p><span style=\"color: rgb(255, 0, 0);\">2、列表直接用“+”功能赋值进行测试即可，无需写代码赋值。</span></p><p><img src=\"https://minio.liankexue.cn/npsc-common-bucket/default/2025-01-22-15-48-32/8570313216872398848.png\" alt=\"\" data-href=\"\" style=\"\"/></p>",
            "referenceAnswer": null,
            "analyzeContent": "<p><span style=\"color: rgb(0, 0, 0);\">【参考程序】</span></p><p><img src=\"https://minio.liankexue.cn/npsc-common-bucket/default/2025-01-22-15-48-43/8570313263273959424.png\" alt=\"\" data-href=\"\" style=\"\"/></p>",
            "analyzeVideo": null,
            "examinationPaperId": "1881967623252123650",
            "markStatus": 1,
            "stemId": null,
            "stemContent": null,
            "score": 25.0,
            "topSubjectDetailId": "1972940117698342914",
            "topSubjectDetailName": "图形化编程",
            "scoreCriteria": null,
            "createTime": "2025-01-22 15:48:45",
            "questionsOptionList": null,
            "questionsKnowledgePointList": [
                {
                    "questionId": "1881972252767866881",
                    "knowledgePointId": "434",
                    "knowledgePoint": "列表的概念"
                },
                {
                    "questionId": "1881972252767866881",
                    "knowledgePointId": "435",
                    "knowledgePoint": "列表的定义、存储、插入、删除"
                },
                {
                    "questionId": "1881972252767866881",
                    "knowledgePointId": "432",
                    "knowledgePoint": "字符串的概念"
                },
                {
                    "questionId": "1881972252767866881",
                    "knowledgePointId": "431",
                    "knowledgePoint": "程序交互设计技巧"
                },
                {
                    "questionId": "1881972252767866881",
                    "knowledgePointId": "430",
                    "knowledgePoint": "计算机的输入、输出功能"
                },
                {
                    "questionId": "1881972252767866881",
                    "knowledgePointId": "441",
                    "knowledgePoint": "基本数据结构"
                }
            ],
            "questionsDetailDTO": null
        },
        {
            "id": "1881972672417812482",
            "examinationPaperTitle": "202403GESP 图形化三级试卷",
            "type": 4,
            "title": "<p><span style=\"color: rgb(0, 0, 0);\">移动 0 元素</span></p><p><img src=\"https://minio.liankexue.cn/npsc-common-bucket/default/2025-01-22-15-48-57/8570313320584929280.png\" alt=\"C1.png\" data-href=\"https://minio.liankexue.cn/npsc-common-bucket/default/2025-01-22-15-48-57/8570313320584929280.png\" style=\"\"/><img src=\"https://minio.liankexue.cn/npsc-common-bucket/default/2025-01-22-15-49-03/8570313343339053056.png\" alt=\"C2.png\" data-href=\"https://minio.liankexue.cn/npsc-common-bucket/default/2025-01-22-15-49-03/8570313343339053056.png\" style=\"\"/></p><p><span style=\"color: rgb(0, 0, 0);\">【题目描述】 </span></p><p><span style=\"color: rgb(0, 0, 0);\">有一组数据存放在列表“list”中，其中包含若干个 0 元素。 </span></p><p><span style=\"color: rgb(0, 0, 0);\">默认小猫角色和白色背景，请将列表中的所有 0 元素移动到列表尾，其余元素的前后顺序不变。 </span></p><p><span style=\"color: rgb(0, 0, 0);\">例如：列表“list”最初存放的数据为[0, 20, 0, 4, 31]，移动 0 元素之后的列表“list”为[20, 4, 31, 0, 0]。 </span></p><p><span style=\"color: rgb(0, 0, 0);\">【输入描述】 </span></p><p><span style=\"color: rgb(0, 0, 0);\">新建列表“list”，用于存放包含 0 元素的数据。 </span></p><p><span style=\"color: rgb(0, 0, 0);\">如下图所示：</span></p><p><img src=\"https://minio.liankexue.cn/npsc-common-bucket/default/2025-01-22-15-49-32/8570313468719357952.png\" alt=\"C3.png\" data-href=\"https://minio.liankexue.cn/npsc-common-bucket/default/2025-01-22-15-49-32/8570313468719357952.png\" style=\"\"/></p><p><span style=\"color: rgb(0, 0, 0);\">【输出描述】 </span></p><p><span style=\"color: rgb(0, 0, 0);\">将 0 元素移动到列表“list”的尾部。最终的结果仍存放在“list”中。 </span></p><p><span style=\"color: rgb(0, 0, 0);\">如下图所示：</span></p><p><img src=\"https://minio.liankexue.cn/npsc-common-bucket/default/2025-01-22-15-49-50/8570313543419912192.png\" alt=\"C4.png\" data-href=\"https://minio.liankexue.cn/npsc-common-bucket/default/2025-01-22-15-49-50/8570313543419912192.png\" style=\"\"/></p><p><span style=\"color: rgb(0, 0, 0);\">【输入样例】 </span></p><p><span style=\"color: rgb(0, 0, 0);\">list = [0, 20, 0, 4, 31] </span></p><p><span style=\"color: rgb(0, 0, 0);\">【输出样例】 </span></p><p><span style=\"color: rgb(0, 0, 0);\">list = [20, 4, 31, 0, 0] </span></p><p><span style=\"color: rgb(0, 0, 0);\">【输入样例】 </span></p><p><span style=\"color: rgb(0, 0, 0);\">list = [0, 7, 0, 22] </span></p><p><span style=\"color: rgb(0, 0, 0);\">【输出样例】 </span></p><p><span style=\"color: rgb(0, 0, 0);\">list = [7, 22, 0, 0]</span></p><p><span style=\"color: rgb(255, 0, 0);\">注意事项： </span></p><p><span style=\"color: rgb(255, 0, 0);\">1、列表名、变量名的拼写（包括大小写）要和题目完全一致。 </span></p><p><span style=\"color: rgb(255, 0, 0);\">2、列表直接用“+”功能赋值进行测试即可，无需写代码赋值。</span></p><p><img src=\"https://minio.liankexue.cn/npsc-common-bucket/default/2025-01-22-15-50-09/8570313622188941312.png\" alt=\"C5.png\" data-href=\"https://minio.liankexue.cn/npsc-common-bucket/default/2025-01-22-15-50-09/8570313622188941312.png\" style=\"\"/></p><p><br></p>",
            "referenceAnswer": null,
            "analyzeContent": "<p><span style=\"color: rgb(0, 0, 0);\">【参考程序】</span></p><p><img src=\"https://minio.liankexue.cn/npsc-common-bucket/default/2025-01-22-15-50-21/8570313674361913344.png\" alt=\"C6.png\" data-href=\"https://minio.liankexue.cn/npsc-common-bucket/default/2025-01-22-15-50-21/8570313674361913344.png\" style=\"\"/></p>",
            "analyzeVideo": null,
            "examinationPaperId": "1881967623252123650",
            "markStatus": 1,
            "stemId": null,
            "stemContent": null,
            "score": 25.0,
            "topSubjectDetailId": "1972940117698342914",
            "topSubjectDetailName": "图形化编程",
            "scoreCriteria": null,
            "createTime": "2025-01-22 15:50:25",
            "questionsOptionList": null,
            "questionsKnowledgePointList": [
                {
                    "questionId": "1881972672417812482",
                    "knowledgePointId": "434",
                    "knowledgePoint": "列表的概念"
                },
                {
                    "questionId": "1881972672417812482",
                    "knowledgePointId": "435",
                    "knowledgePoint": "列表的定义、存储、插入、删除"
                },
                {
                    "questionId": "1881972672417812482",
                    "knowledgePointId": "441",
                    "knowledgePoint": "基本数据结构"
                }
            ],
            "questionsDetailDTO": null
        }
    ]
}